robotics_dev/__init__.py
robotics_dev/robotics.py
robotics_dev-0.0.17.dist-info/METADATA
robotics_dev-0.0.17.dist-info/WHEEL
robotics_dev-0.0.17.dist-info/licenses/LICENSE.md
robotics_dev-0.0.17.dist-info/RECORD
