Metadata-Version: 2.4
Name: robotics-dev
Version: 0.0.17
Summary: Robotics.dev AI robotics app builder
Project-URL: Homepage, https://robotics.dev
Project-URL: Repository, https://github.com/roboticshq/robotics-pip.git
Project-URL: Issues, https://github.com/roboticshq/robotics-pip/issues
Author-email: Chris Matthieu <chris@matthieu.us>
License: PolyForm Noncommercial License 1.0.0
License-File: LICENSE.md
Keywords: AI,ROS,ROS2,motors,robotics,robots,streaming,video
Classifier: License :: Other/Proprietary License
Classifier: Operating System :: OS Independent
Classifier: Programming Language :: Python :: 3
Requires-Python: >=3.8
Requires-Dist: aiohttp
Requires-Dist: aiortc
Requires-Dist: lzstring
Requires-Dist: python-socketio
Requires-Dist: python-socketio[client]
